
{
  "2025-04": [
    { "day": 7, "desc": "TDS/TCS Payment (Mar)", "cat": "tds" },
    { "day": 10, "desc": "GSTR-7 (Mar)", "cat": "gst" },
    { "day": 10, "desc": "GSTR-8 (Mar)", "cat": "gst" },
    { "day": 11, "desc": "GSTR-1 (Monthly Mar)", "cat": "gst" },
    { "day": 13, "desc": "GSTR-1 IFF (Optional Mar)", "cat": "gst" },
    { "day": 13, "desc": "GSTR-5 & 6 (Mar)", "cat": "gst" },
    { "day": 15, "desc": "PF & ESI Payment (Mar)", "cat": "payroll" },
    { "day": 18, "desc": "CMP-08 (Jan-Mar)", "cat": "gst" },
    { "day": 20, "desc": "GSTR-3B (Monthly Mar)", "cat": "gst" },
    { "day": 20, "desc": "PT Payment (Karnataka Mar)", "cat": "payroll" },
    { "day": 22, "desc": "GSTR-3B Qtly (Jan-Mar)", "cat": "gst" },
    { "day": 30, "desc": "MSME-1 (Oct-Mar)", "cat": "roc" },
    { "day": 30, "desc": "GSTR-4 Annual (FY 24-25)", "cat": "gst" },
    { "day": 30, "desc": "PT Annual Return (FY 24-25)", "cat": "payroll" },
    { "day": 30, "desc": "TDS Return Q4 (Jan-Mar)", "cat": "tds" }
  ],
  "2025-05": [
    { "day": 7, "desc": "TDS/TCS Payment (Apr)", "cat": "tds" },
    { "day": 10, "desc": "GSTR-7 (Apr)", "cat": "gst" },
    { "day": 10, "desc": "GSTR-8 (Apr)", "cat": "gst" },
    { "day": 11, "desc": "GSTR-1 (Monthly Apr)", "cat": "gst" },
    { "day": 15, "desc": "TCS Return Q4 (Jan-Mar)", "cat": "tds" },
    { "day": 15, "desc": "PF & ESI Payment (Apr)", "cat": "payroll" },
    { "day": 20, "desc": "GSTR-3B (Monthly Apr)", "cat": "gst" },
    { "day": 20, "desc": "PT Payment (Apr)", "cat": "payroll" },
    { "day": 30, "desc": "LLP Form 11 Annual (FY 24-25)", "cat": "roc" },
    { "day": 30, "desc": "PAS-6 (Oct-Mar)", "cat": "roc" },
    { "day": 31, "desc": "Issue Form 16A (Q4)", "cat": "tds" }
  ],
  "2025-06": [
    { "day": 7, "desc": "TDS/TCS Payment (May)", "cat": "tds" },
    { "day": 10, "desc": "GSTR-7 (May)", "cat": "gst" },
    { "day": 10, "desc": "GSTR-8 (May)", "cat": "gst" },
    { "day": 11, "desc": "GSTR-1 (Monthly May)", "cat": "gst" },
    { "day": 15, "desc": "Advance Tax 1st Inst. (15%)", "cat": "it" },
    { "day": 15, "desc": "Issue Form 16 (Salary)", "cat": "it" },
    { "day": 15, "desc": "Issue TCS Cert (Q4)", "cat": "tds" },
    { "day": 15, "desc": "PF & ESI Payment (May)", "cat": "payroll" },
    { "day": 20, "desc": "GSTR-3B (Monthly May)", "cat": "gst" },
    { "day": 20, "desc": "PT Payment (May)", "cat": "payroll" },
    { "day": 29, "desc": "DPT-3 Return of Deposits", "cat": "roc" }
  ],
  "2025-07": [
    { "day": 7, "desc": "TDS/TCS Payment (Jun)", "cat": "tds" },
    { "day": 10, "desc": "GSTR-7 (Jun)", "cat": "gst" },
    { "day": 10, "desc": "GSTR-8 (Jun)", "cat": "gst" },
    { "day": 11, "desc": "GSTR-1 (Monthly Jun)", "cat": "gst" },
    { "day": 13, "desc": "GSTR-1 Qtly (Apr-Jun)", "cat": "gst" },
    { "day": 15, "desc": "TCS Return Q1 (Apr-Jun)", "cat": "tds" },
    { "day": 15, "desc": "PF & ESI Payment (Jun)", "cat": "payroll" },
    { "day": 15, "desc": "FLA Return (RBI)", "cat": "roc" },
    { "day": 18, "desc": "CMP-08 (Apr-Jun)", "cat": "gst" },
    { "day": 20, "desc": "GSTR-3B (Monthly Jun)", "cat": "gst" },
    { "day": 20, "desc": "PT Payment (Jun)", "cat": "payroll" },
    { "day": 22, "desc": "GSTR-3B Qtly (Apr-Jun)", "cat": "gst" },
    { "day": 31, "desc": "TDS Return Q1 (Apr-Jun)", "cat": "tds" },
    { "day": 31, "desc": "ITR Filing (Non-Audit)", "cat": "it" }
  ],
  "2025-08": [
    { "day": 7, "desc": "TDS/TCS Payment (Jul)", "cat": "tds" },
    { "day": 10, "desc": "GSTR-7 (Jul)", "cat": "gst" },
    { "day": 10, "desc": "GSTR-8 (Jul)", "cat": "gst" },
    { "day": 11, "desc": "GSTR-1 (Monthly Jul)", "cat": "gst" },
    { "day": 15, "desc": "Issue Form 16A (Q1)", "cat": "tds" },
    { "day": 15, "desc": "PF & ESI Payment (Jul)", "cat": "payroll" },
    { "day": 20, "desc": "GSTR-3B (Monthly Jul)", "cat": "gst" },
    { "day": 20, "desc": "PT Payment (Jul)", "cat": "payroll" }
  ],
  "2025-09": [
    { "day": 7, "desc": "TDS/TCS Payment (Aug)", "cat": "tds" },
    { "day": 10, "desc": "GSTR-7 (Aug)", "cat": "gst" },
    { "day": 10, "desc": "GSTR-8 (Aug)", "cat": "gst" },
    { "day": 11, "desc": "GSTR-1 (Monthly Aug)", "cat": "gst" },
    { "day": 15, "desc": "ITR Non-Audit (Extended)", "cat": "it" },
    { "day": 15, "desc": "Advance Tax 2nd Inst. (45%)", "cat": "it" },
    { "day": 15, "desc": "PF & ESI Payment (Aug)", "cat": "payroll" },
    { "day": 20, "desc": "GSTR-3B (Monthly Aug)", "cat": "gst" },
    { "day": 20, "desc": "PT Payment (Aug)", "cat": "payroll" },
    { "day": 30, "desc": "AGM Due Date", "cat": "roc" }
  ],
  "2025-10": [
    { "day": 7, "desc": "TDS/TCS Payment (Sep)", "cat": "tds" },
    { "day": 10, "desc": "GSTR-7 (Sep)", "cat": "gst" },
    { "day": 10, "desc": "GSTR-8 (Sep)", "cat": "gst" },
    { "day": 11, "desc": "GSTR-1 (Monthly Sep)", "cat": "gst" },
    { "day": 13, "desc": "GSTR-1 Qtly (Jul-Sep)", "cat": "gst" },
    { "day": 14, "desc": "ADT-1 Auditor Appt", "cat": "roc" },
    { "day": 15, "desc": "DIR-3 KYC Extended", "cat": "roc" },
    { "day": 15, "desc": "TCS Return Q2 (Jul-Sep)", "cat": "tds" },
    { "day": 15, "desc": "PF & ESI Payment (Sep)", "cat": "payroll" },
    { "day": 18, "desc": "CMP-08 (Jul-Sep)", "cat": "gst" },
    { "day": 20, "desc": "PT Payment (Sep)", "cat": "payroll" },
    { "day": 22, "desc": "GSTR-3B Qtly (Jul-Sep)", "cat": "gst" },
    { "day": 25, "desc": "GSTR-3B Monthly Extended", "cat": "gst" },
    { "day": 30, "desc": "LLP Form 8 (Solvency)", "cat": "roc" },
    { "day": 31, "desc": "TDS Return Q2 (Jul-Sep)", "cat": "tds" },
    { "day": 31, "desc": "MSME-1 (Apr-Sep)", "cat": "roc" }
  ],
  "2025-11": [
    { "day": 7, "desc": "TDS/TCS Payment (Oct)", "cat": "tds" },
    { "day": 10, "desc": "GSTR-7 (Oct)", "cat": "gst" },
    { "day": 10, "desc": "GSTR-8 (Oct)", "cat": "gst" },
    { "day": 10, "desc": "Tax Audit Report Extended", "cat": "it" },
    { "day": 11, "desc": "GSTR-1 (Monthly Oct)", "cat": "gst" },
    { "day": 14, "desc": "Issue Form 16A (Q2)", "cat": "tds" },
    { "day": 15, "desc": "PF & ESI Payment (Oct)", "cat": "payroll" },
    { "day": 20, "desc": "GSTR-3B (Monthly Oct)", "cat": "gst" },
    { "day": 20, "desc": "PT Payment (Oct)", "cat": "payroll" },
    { "day": 29, "desc": "PAS-6 (Apr-Sep)", "cat": "roc" },
    { "day": 30, "desc": "Form 3CEB Transfer Pricing", "cat": "it" }
  ],
  "2025-12": [
    { "day": 7, "desc": "TDS/TCS Payment (Nov)", "cat": "tds" },
    { "day": 10, "desc": "GSTR-7 (Nov)", "cat": "gst" },
    { "day": 10, "desc": "GSTR-8 (Nov)", "cat": "gst" },
    { "day": 10, "desc": "ITR Audit Cases Extended", "cat": "it" },
    { "day": 11, "desc": "GSTR-1 (Monthly Nov)", "cat": "gst" },
    { "day": 15, "desc": "Advance Tax 3rd Inst. (75%)", "cat": "it" },
    { "day": 15, "desc": "PF & ESI Payment (Nov)", "cat": "payroll" },
    { "day": 20, "desc": "GSTR-3B (Monthly Nov)", "cat": "gst" },
    { "day": 20, "desc": "PT Payment (Nov)", "cat": "payroll" },
    { "day": 31, "desc": "AOC-4 & MGT-7 Extended", "cat": "roc" },
    { "day": 31, "desc": "GSTR-9 & 9C Annual (FY 24-25)", "cat": "gst" },
    { "day": 31, "desc": "Belated/Revised ITR (FY 24-25)", "cat": "it" }
  ],
  "2026-01": [
    { "day": 7, "desc": "TDS/TCS Payment (Dec)", "cat": "tds" },
    { "day": 10, "desc": "GSTR-7 (Dec)", "cat": "gst" },
    { "day": 10, "desc": "GSTR-8 (Dec)", "cat": "gst" },
    { "day": 11, "desc": "GSTR-1 (Monthly Dec)", "cat": "gst" },
    { "day": 13, "desc": "GSTR-1 Qtly (Oct-Dec)", "cat": "gst" },
    { "day": 15, "desc": "TCS Return Q3 (Oct-Dec)", "cat": "tds" },
    { "day": 15, "desc": "PF & ESI Payment (Dec)", "cat": "payroll" },
    { "day": 18, "desc": "CMP-08 (Oct-Dec)", "cat": "gst" },
    { "day": 20, "desc": "GSTR-3B (Monthly Dec)", "cat": "gst" },
    { "day": 20, "desc": "PT Payment (Dec)", "cat": "payroll" },
    { "day": 22, "desc": "GSTR-3B Qtly (Oct-Dec)", "cat": "gst" },
    { "day": 31, "desc": "TDS Return Q3 (Oct-Dec)", "cat": "tds" }
  ],
  "2026-02": [
    { "day": 7, "desc": "TDS/TCS Payment (Jan)", "cat": "tds" },
    { "day": 10, "desc": "GSTR-7 (Jan)", "cat": "gst" },
    { "day": 10, "desc": "GSTR-8 (Jan)", "cat": "gst" },
    { "day": 11, "desc": "GSTR-1 (Monthly Jan)", "cat": "gst" },
    { "day": 14, "desc": "Issue Form 16A (Q3)", "cat": "tds" },
    { "day": 15, "desc": "PF & ESI Payment (Jan)", "cat": "payroll" },
    { "day": 20, "desc": "GSTR-3B (Monthly Jan)", "cat": "gst" },
    { "day": 20, "desc": "PT Payment (Jan)", "cat": "payroll" }
  ],
  "2026-03": [
    { "day": 7, "desc": "TDS/TCS Payment (Feb)", "cat": "tds" },
    { "day": 10, "desc": "GSTR-7 (Feb)", "cat": "gst" },
    { "day": 10, "desc": "GSTR-8 (Feb)", "cat": "gst" },
    { "day": 11, "desc": "GSTR-1 (Monthly Feb)", "cat": "gst" },
    { "day": 15, "desc": "Advance Tax 4th Inst. (100%)", "cat": "it" },
    { "day": 15, "desc": "PF & ESI Payment (Feb)", "cat": "payroll" },
    { "day": 20, "desc": "GSTR-3B (Monthly Feb)", "cat": "gst" },
    { "day": 20, "desc": "PT Payment (Feb)", "cat": "payroll" },
    { "day": 31, "desc": "ITR-U Last Date (FY 22-23)", "cat": "it" }
  ]
}
